yt_chap/__init__.py
yt_chap/cli.py
yt_chap-0.3.0.dist-info/licenses/LICENSE
yt_chap-0.3.0.dist-info/METADATA
yt_chap-0.3.0.dist-info/WHEEL
yt_chap-0.3.0.dist-info/entry_points.txt
yt_chap-0.3.0.dist-info/top_level.txt
yt_chap-0.3.0.dist-info/RECORD
