Metadata-Version: 2.4
Name: yt-chap
Version: 0.3.0
Summary: CLI tool to display YouTube chapters using yt-dlp
Home-page: https://github.com/mallikmusaddiq1/yt-chap
Author: Mallik Mohammad Musaddiq
Author-email: mallikmusaddiq1@gmail.com
Classifier: Programming Language :: Python :: 3
Classifier: License :: OSI Approved :: MIT License
Classifier: Operating System :: OS Independent
Classifier: Environment :: Console
Classifier: Topic :: Utilities
Requires-Python: >=3.6
License-File: LICENSE
Dynamic: author
Dynamic: author-email
Dynamic: classifier
Dynamic: home-page
Dynamic: license-file
Dynamic: requires-python
Dynamic: summary
